babySql/__init__.py
babySql/class_methods/__init__.py
babySql/class_methods/cm_mariadb.py
babySql/class_methods/cm_mysql.py
babySql/class_methods/cm_postgresql.py
babySql/class_methods/cm_sqlite.py
babySql/tools/__init__.py
babySql/tools/create/__init__.py
babySql/tools/create/c_mariadb.py
babySql/tools/create/c_mysql.py
babySql/tools/create/c_postgresql.py
babySql/tools/create/c_sqlite.py
babySql/tools/select/__init__.py
babySql/tools/select/s_base.py
babySql/tools/select/s_mariadb.py
babySql/tools/select/s_mysql.py
babySql/tools/select/s_postgresql.py
babySql/tools/select/s_sqlite.py
babysql-0.1.0.2.dist-info/METADATA
babysql-0.1.0.2.dist-info/WHEEL
babysql-0.1.0.2.dist-info/top_level.txt
babysql-0.1.0.2.dist-info/RECORD
