Metadata-Version: 2.4
Name: babySql
Version: 0.1.0.2
Summary: 基于各数据库连接包的二次开发SQL连接工具
Home-page: https://github.com/yanshi121/BabySql
Author: 39
Author-email: DY39project@outlook.com
Classifier: Programming Language :: Python :: 3
Classifier: License :: OSI Approved :: MIT License
Classifier: Operating System :: Microsoft :: Windows
Classifier: Operating System :: POSIX :: Linux
Requires-Python: >=3.5
Requires-Dist: pymysql
Requires-Dist: dbutils
Requires-Dist: psycopg2
Dynamic: author
Dynamic: author-email
Dynamic: classifier
Dynamic: description
Dynamic: description-content-type
Dynamic: home-page
Dynamic: requires-dist
Dynamic: requires-python
Dynamic: summary
